ibmJupyterNotebookStyles/CustomColorMaps.py
ibmJupyterNotebookStyles/CustomCssStyling.py
ibmJupyterNotebookStyles/CustomMplStyle.py
ibmJupyterNotebookStyles/StylingBase.py
ibmJupyterNotebookStyles/__init__.py
ibmJupyterNotebookStyles/ibm.mplstyle
ibmJupyterNotebookStyles-0.0.7.dist-info/LICENSE
ibmJupyterNotebookStyles-0.0.7.dist-info/METADATA
ibmJupyterNotebookStyles-0.0.7.dist-info/WHEEL
ibmJupyterNotebookStyles-0.0.7.dist-info/top_level.txt
ibmJupyterNotebookStyles-0.0.7.dist-info/RECORD
