Metadata-Version: 2.1
Name: ibmJupyterNotebookStyles
Version: 0.0.7
Summary: IBM Jupyter Notebook Styles
Home-page: UNKNOWN
Author: (IBM)
Author-email: <ionut.chereji@ro.ibm.com>
License: MIT
Keywords: ibm,style
Platform: UNKNOWN
Classifier: Development Status :: 4 - Beta
Classifier: Intended Audience :: Developers
Classifier: Programming Language :: Python :: 3
Classifier: Operating System :: Unix
Classifier: Operating System :: MacOS :: MacOS X
Classifier: Operating System :: Microsoft :: Windows
Requires-Dist: matplotlib
